geiger/__init__.py
geiger/algorithms/__init__.py
geiger/algorithms/deconvolution.py
geiger/algorithms/spectral_response_matrix.py
geiger/core/__init__.py
geiger/core/base_classes.py
geiger/core/calibration.py
geiger/core/counts.py
geiger/core/spectrum.py
geiger/utilities/__init__.py
geiger/utilities/plotting.py
geiger-0.0.3.dist-info/LICENSE
geiger-0.0.3.dist-info/METADATA
geiger-0.0.3.dist-info/WHEEL
geiger-0.0.3.dist-info/top_level.txt
geiger-0.0.3.dist-info/RECORD
