Metadata-Version: 2.1
Name: geiger
Version: 0.0.3
Summary: A radiation detection utility package
Home-page: https://github.com/iandellarocca/geiger
Author: Ian Della-Rocca
Author-email: ian.dellarocca@gmail.com
License: UNKNOWN
Project-URL: Bug Tracker, https://github.com/iandellarocca/geiger/issues
Platform: UNKNOWN
Classifier: Programming Language :: Python :: 3
Classifier: License :: OSI Approved :: MIT License
Classifier: Operating System :: OS Independent
Requires-Python: >=3.6
License-File: LICENSE
